fastjws/__init__.py
fastjws/jws.py
fastjws-1.1.0.dist-info/LICENSE
fastjws-1.1.0.dist-info/METADATA
fastjws-1.1.0.dist-info/WHEEL
fastjws-1.1.0.dist-info/top_level.txt
fastjws-1.1.0.dist-info/RECORD
