Metadata-Version: 2.1
Name: fastjws
Version: 1.1.0
Summary: This library will help you use JWT authentication in FastAPI!
Home-page: https://github.com/Eugenekochetov02/fastjws
Author: EugeneKo
Author-email: eugene.kochetov02@gmail.com
Keywords: example python
Classifier: Programming Language :: Python :: 3.11
Classifier: License :: OSI Approved :: MIT License
Classifier: Operating System :: OS Independent
Requires-Python: >=3.10
License-File: LICENSE
Requires-Dist: fastapi (>=0.103.1)
Requires-Dist: python-jose (>=3.3.0)
